nnvis/__init__.py
nnvis/data_loader.py
nnvis/examine1D.py
nnvis/examine2D.py
nnvis/examine_surface.py
nnvis/net.py
nnvis/paths.py
nnvis/plot.py
nnvis/prelim.py
nnvis-1.1.4.dist-info/LICENSE.txt
nnvis-1.1.4.dist-info/METADATA
nnvis-1.1.4.dist-info/WHEEL
nnvis-1.1.4.dist-info/top_level.txt
nnvis-1.1.4.dist-info/RECORD
