Metadata-Version: 2.1
Name: nnvis
Version: 1.1.4
Summary: Visualizing tool for PyTorch NN models
Home-page: UNKNOWN
Author: Silvie Němcová
Author-email: nemcova.silva@gmail.com
License: MIT
Project-URL: Source, https://github.com/suzrz/nnvis
Project-URL: Tracker, https://github.com/suzrz/nnvis/issues
Platform: UNKNOWN
Classifier: Development Status :: 4 - Beta
Classifier: Environment :: Console
Classifier: Environment :: GPU :: NVIDIA CUDA :: 11.1
Classifier: Environment :: MacOS X
Classifier: Intended Audience :: Education
Classifier: Intended Audience :: Information Technology
Classifier: Intended Audience :: Science/Research
Classifier: License :: OSI Approved :: MIT License
Classifier: Operating System :: OS Independent
Classifier: Programming Language :: Python :: 3
Classifier: Topic :: Scientific/Engineering :: Artificial Intelligence
Classifier: Topic :: Scientific/Engineering :: Image Processing
Classifier: Topic :: Scientific/Engineering :: Image Recognition
Classifier: Topic :: Scientific/Engineering :: Visualization
Classifier: Topic :: Utilities
License-File: LICENSE.txt
Requires-Dist: numpy
Requires-Dist: torch (>=1.8.1)
Requires-Dist: torchvision (>=0.9.1)
Requires-Dist: scipy
Requires-Dist: sklearn
Requires-Dist: matplotlib
Requires-Dist: h5py
Requires-Dist: tqdm
